kumiho/__init__.py
kumiho/_bootstrap.py
kumiho/_token_loader.py
kumiho/artifact.py
kumiho/auth_cli.py
kumiho/base.py
kumiho/bundle.py
kumiho/client.py
kumiho/discovery.py
kumiho/edge.py
kumiho/event.py
kumiho/item.py
kumiho/kref.py
kumiho/mcp_server.py
kumiho/project.py
kumiho/py.typed
kumiho/revision.py
kumiho/space.py
kumiho/proto/__init__.py
kumiho/proto/kumiho_pb2.py
kumiho/proto/kumiho_pb2.pyi
kumiho/proto/kumiho_pb2_grpc.py
kumiho-0.9.1.dist-info/licenses/LICENSE
kumiho-0.9.1.dist-info/METADATA
kumiho-0.9.1.dist-info/WHEEL
kumiho-0.9.1.dist-info/entry_points.txt
kumiho-0.9.1.dist-info/top_level.txt
kumiho-0.9.1.dist-info/RECORD
