Metadata-Version: 2.4
Name: kumiho
Version: 0.9.1
Summary: Python SDK for Kumiho Cloud - Graph-native creative & AI asset management
Author-email: Kumiho Clouds <support@kumiho.cloud>
Maintainer-email: Kumiho Clouds <support@kumiho.cloud>
License-Expression: MIT
Project-URL: Homepage, https://kumiho.io
Project-URL: Documentation, https://docs.kumiho.io
Project-URL: Repository, https://github.com/kumihoclouds/kumiho-python
Project-URL: Changelog, https://github.com/kumihoclouds/kumiho-python/blob/main/CHANGELOG.md
Project-URL: Issues, https://github.com/kumihoclouds/kumiho-python/issues
Keywords: kumiho,asset-management,version-control,graph-database,vfx,creative,ai-assets,lineage,neo4j,mcp,model-context-protocol
Classifier: Development Status :: 4 - Beta
Classifier: Intended Audience :: Developers
Classifier: Intended Audience :: Science/Research
Classifier: Operating System :: OS Independent
Classifier: Programming Language :: Python :: 3
Classifier: Programming Language :: Python :: 3.10
Classifier: Programming Language :: Python :: 3.11
Classifier: Programming Language :: Python :: 3.12
Classifier: Topic :: Multimedia :: Graphics
Classifier: Topic :: Scientific/Engineering :: Artificial Intelligence
Classifier: Topic :: Software Development :: Version Control
Classifier: Typing :: Typed
Requires-Python: >=3.10
License-File: LICENSE
Requires-Dist: grpcio>=1.76.0
Requires-Dist: grpcio-tools>=1.76.0
Requires-Dist: protobuf>=6.31.1
Requires-Dist: requests>=2.31.0
Provides-Extra: dev
Requires-Dist: pytest>=8.2.0; extra == "dev"
Requires-Dist: pytest-cov>=4.1.0; extra == "dev"
Requires-Dist: mypy>=1.8.0; extra == "dev"
Requires-Dist: types-requests>=2.31.0; extra == "dev"
Provides-Extra: docs
Requires-Dist: sphinx>=7.0.0; extra == "docs"
Requires-Dist: sphinx-rtd-theme>=2.0.0; extra == "docs"
Requires-Dist: sphinx-autodoc-typehints>=1.25.0; extra == "docs"
Requires-Dist: myst-parser>=2.0.0; extra == "docs"
Provides-Extra: mcp
Requires-Dist: mcp>=1.0.0; extra == "mcp"
Requires-Dist: httpx>=0.27.0; extra == "mcp"
Provides-Extra: all
Requires-Dist: kumiho[dev,docs,mcp]; extra == "all"
Dynamic: license-file
